naneos_backend/__init__.py
naneos_backend/logger.py
naneos_backend/ble/__init__.py
naneos_backend/ble/ble.py
naneos_backend/commands/__init__.py
naneos_backend/commands/commands.py
naneos_backend/commands/src/__init__.py
naneos_backend/commands/src/p2_cmd.py
naneos_backend/commands/src/silent_pump_cmd.py
naneos_backend/devices/__init__.py
naneos_backend/devices/ble_device.py
naneos_backend/devices/device.py
naneos_backend/devices/serial_device.py
naneos_backend/devices/naneos/__init__.py
naneos_backend/devices/naneos/naneos_measurement_dataclass.py
naneos_backend/devices/naneos/partector2.py
naneos_backend/devices/naneos/silentPump.py
naneos_backend/devices/third_party/__init__.py
naneos_backend/devices/third_party/defender.py
naneos_backend/influx/__init__.py
naneos_backend/influx/credentials.py
naneos_backend/influx/influx.py
naneos_backend/influx/influx_db_management.py
naneos_backend/influx/p2_to_naneos_influx.py
naneos_backend/port_scanning/__init__.py
naneos_backend/port_scanning/device_mapping.py
naneos_backend/port_scanning/port_scan.py
naneos_backend/port_scanning/port_scan_wrappers.py
naneos_backend/port_scanning/scan_devices.py
naneos_backend/upload/__init__.py
naneos_backend/upload/lambda_upload_http.py
naneos_backend-1.2.0.dist-info/LICENSE
naneos_backend-1.2.0.dist-info/METADATA
naneos_backend-1.2.0.dist-info/WHEEL
naneos_backend-1.2.0.dist-info/top_level.txt
naneos_backend-1.2.0.dist-info/RECORD
