Metadata-Version: 2.1
Name: naneos-backend
Version: 1.2.0
Summary: Python Toolkit backend for communication with naneos and 3rd party devices.
Home-page: https://github.com/naneos-org/python-naneos-backend
Author: huegi
Author-email: mario.huegi@naneos.ch
License: MIT
Platform: UNKNOWN
Classifier: Programming Language :: Python :: 3
Classifier: Operating System :: Unix
Classifier: Operating System :: MacOS :: MacOS X
Classifier: Operating System :: Microsoft :: Windows
License-File: LICENSE
Requires-Dist: pyserial
Requires-Dist: numpy
Requires-Dist: pandas
Requires-Dist: influxdb-client
Requires-Dist: bleak
Requires-Dist: requests
